README.rst
setup.py
fnvhash/__init__.py
fnvhash.egg-info/PKG-INFO
fnvhash.egg-info/SOURCES.txt
fnvhash.egg-info/dependency_links.txt
fnvhash.egg-info/top_level.txt
fnvhash.egg-info/zip-safe